ndtransform/__init__.py
ndtransform/nDtransform_lib.py
ndtransform-0.1.3.dist-info/METADATA
ndtransform-0.1.3.dist-info/WHEEL
ndtransform-0.1.3.dist-info/RECORD
