Metadata-Version: 2.1
Name: ndtransform
Version: 0.1.3
Summary: 
Author: sevolek
Author-email: ale.sev@outlook.com
Requires-Python: >=3.11,<4.0
Classifier: Programming Language :: Python :: 3
Classifier: Programming Language :: Python :: 3.11
Requires-Dist: numpy (>=1.24.3,<2.0.0)
